[
  {
    "candidate_id": "score_f12_prob_f12",
    "passed": true,
    "error": "",
    "score_frac": 12,
    "prob_frac": 12,
    "total_internal_bits": 215,
    "worst_mean_abs_error": 0.00016695874835413637,
    "worst_max_abs_error": 0.05644679012299747,
    "worst_rmse": 0.001720862368432083,
    "per_seed": [
      {
        "seed": 0,
        "mean_abs_error": 3.771497479852003e-05,
        "max_abs_error": 0.024320396348130657,
        "rmse": 0.0007295616256654822
      },
      {
        "seed": 1,
        "mean_abs_error": 4.606159704436785e-06,
        "max_abs_error": 0.002676013313873682,
        "rmse": 7.925895897283765e-05
      },
      {
        "seed": 2,
        "mean_abs_error": 4.379155810816471e-05,
        "max_abs_error": 0.01864434753396438,
        "rmse": 0.0006249446553998357
      },
      {
        "seed": 3,
        "mean_abs_error": 9.141419491397078e-06,
        "max_abs_error": 0.0034767565004045764,
        "rmse": 0.00012414650087088996
      },
      {
        "seed": 4,
        "mean_abs_error": 8.320278434782349e-05,
        "max_abs_error": 0.05399627281902042,
        "rmse": 0.0014847868735404304
      },
      {
        "seed": 5,
        "mean_abs_error": 4.277066308396797e-05,
        "max_abs_error": 0.029924219517454276,
        "rmse": 0.0008171219702237404
      },
      {
        "seed": 6,
        "mean_abs_error": 2.4940622818606247e-08,
        "max_abs_error": 1.2143602333480885e-05,
        "rmse": 3.767093532981776e-07
      },
      {
        "seed": 7,
        "mean_abs_error": 1.3853156539291283e-06,
        "max_abs_error": 0.0010130609300773585,
        "rmse": 2.707290238916406e-05
      },
      {
        "seed": 8,
        "mean_abs_error": 3.150160954675162e-12,
        "max_abs_error": 2.0122286059631733e-09,
        "rmse": 6.253094664048602e-11
      },
      {
        "seed": 9,
        "mean_abs_error": 9.778507321604798e-05,
        "max_abs_error": 0.05050869681328152,
        "rmse": 0.0014927374110051577
      },
      {
        "seed": 10,
        "mean_abs_error": 3.854440484700924e-05,
        "max_abs_error": 0.028964940747925993,
        "rmse": 0.0007568725882474468
      },
      {
        "seed": 11,
        "mean_abs_error": 1.4214481803778436e-05,
        "max_abs_error": 0.0070932409120985085,
        "rmse": 0.0002074007024943119
      },
      {
        "seed": 12,
        "mean_abs_error": 5.017574720800988e-05,
        "max_abs_error": 0.023840339585291304,
        "rmse": 0.0007853839738415031
      },
      {
        "seed": 13,
        "mean_abs_error": 3.856090051341493e-05,
        "max_abs_error": 0.02344305701888061,
        "rmse": 0.000723170950606548
      },
      {
        "seed": 14,
        "mean_abs_error": 7.473462083534679e-06,
        "max_abs_error": 0.0029050979562299517,
        "rmse": 0.00010720174524567456
      },
      {
        "seed": 15,
        "mean_abs_error": 2.3136252289464354e-05,
        "max_abs_error": 0.01861194371034003,
        "rmse": 0.00048200268961566246
      },
      {
        "seed": 16,
        "mean_abs_error": 1.577428515742702e-05,
        "max_abs_error": 0.01008632165473955,
        "rmse": 0.00027978474894202357
      },
      {
        "seed": 17,
        "mean_abs_error": 0.00011441647149931509,
        "max_abs_error": 0.0435573497685553,
        "rmse": 0.0015403756596342952
      },
      {
        "seed": 18,
        "mean_abs_error": 4.0336223978176536e-05,
        "max_abs_error": 0.029163875054564414,
        "rmse": 0.0007870941163574257
      },
      {
        "seed": 19,
        "mean_abs_error": 2.3729333636011626e-05,
        "max_abs_error": 0.014002804943388014,
        "rmse": 0.0004405669439635875
      },
      {
        "seed": 20,
        "mean_abs_error": 1.1402026587182824e-05,
        "max_abs_error": 0.007552350496126792,
        "rmse": 0.000216000951120046
      },
      {
        "seed": 21,
        "mean_abs_error": 2.2991542775839882e-05,
        "max_abs_error": 0.011726603925410473,
        "rmse": 0.00035016125344752787
      },
      {
        "seed": 22,
        "mean_abs_error": 4.931268443379701e-05,
        "max_abs_error": 0.02168176856463333,
        "rmse": 0.0007231807513797633
      },
      {
        "seed": 23,
        "mean_abs_error": 2.9249169365463945e-05,
        "max_abs_error": 0.017416367117576215,
        "rmse": 0.0005612831689291562
      },
      {
        "seed": 24,
        "mean_abs_error": 6.870002641595383e-06,
        "max_abs_error": 0.002749862103073042,
        "rmse": 9.831063462162196e-05
      },
      {
        "seed": 25,
        "mean_abs_error": 5.633228762615793e-06,
        "max_abs_error": 0.003934620189852467,
        "rmse": 0.00011184196529364978
      },
      {
        "seed": 26,
        "mean_abs_error": 8.946133469186189e-08,
        "max_abs_error": 5.521726460244736e-05,
        "rmse": 1.7042263410597434e-06
      },
      {
        "seed": 27,
        "mean_abs_error": 3.405771278330911e-10,
        "max_abs_error": 1.4520695401643025e-07,
        "rmse": 4.706843223504854e-09
      },
      {
        "seed": 28,
        "mean_abs_error": 1.6516795865595746e-05,
        "max_abs_error": 0.01069169619358945,
        "rmse": 0.00029908229162244315
      },
      {
        "seed": 29,
        "mean_abs_error": 4.191825148147741e-05,
        "max_abs_error": 0.026339476875520518,
        "rmse": 0.000741534778213856
      },
      {
        "seed": 30,
        "mean_abs_error": 7.182456428108074e-08,
        "max_abs_error": 4.790462617165758e-05,
        "rmse": 1.2739199871995192e-06
      },
      {
        "seed": 31,
        "mean_abs_error": 6.377310413101395e-05,
        "max_abs_error": 0.044152927830772626,
        "rmse": 0.0012177573879871802
      },
      {
        "seed": 32,
        "mean_abs_error": 6.764811992665887e-10,
        "max_abs_error": 3.9571916943259566e-07,
        "rmse": 1.2936179415960111e-08
      },
      {
        "seed": 33,
        "mean_abs_error": 0.00010907767912713125,
        "max_abs_error": 0.045486503660917776,
        "rmse": 0.0014812994391967345
      },
      {
        "seed": 34,
        "mean_abs_error": 1.3127848973015008e-05,
        "max_abs_error": 0.009329960343265498,
        "rmse": 0.00025877631104204125
      },
      {
        "seed": 35,
        "mean_abs_error": 3.1952280173704334e-05,
        "max_abs_error": 0.016715765845901842,
        "rmse": 0.0004823264547993354
      },
      {
        "seed": 36,
        "mean_abs_error": 2.2035252390963135e-06,
        "max_abs_error": 0.001544816328816978,
        "rmse": 4.29636618544349e-05
      },
      {
        "seed": 37,
        "mean_abs_error": 2.462699488412279e-05,
        "max_abs_error": 0.015279430089563562,
        "rmse": 0.00041383526401919847
      },
      {
        "seed": 38,
        "mean_abs_error": 7.24045192832673e-05,
        "max_abs_error": 0.03642079049690494,
        "rmse": 0.0011320393871144144
      },
      {
        "seed": 39,
        "mean_abs_error": 3.8384874775730155e-05,
        "max_abs_error": 0.015431446585225217,
        "rmse": 0.0005002216998142488
      },
      {
        "seed": 40,
        "mean_abs_error": 0.0001338256779353392,
        "max_abs_error": 0.04952764011507327,
        "rmse": 0.0016387393851422039
      },
      {
        "seed": 41,
        "mean_abs_error": 2.0817773324030447e-05,
        "max_abs_error": 0.013312283790050117,
        "rmse": 0.00035802350899971034
      },
      {
        "seed": 42,
        "mean_abs_error": 6.215363004401068e-05,
        "max_abs_error": 0.014664581853949699,
        "rmse": 0.0006289739954160304
      },
      {
        "seed": 43,
        "mean_abs_error": 6.006452377724906e-05,
        "max_abs_error": 0.037407232704538274,
        "rmse": 0.0010473005793394032
      },
      {
        "seed": 44,
        "mean_abs_error": 1.021511517989772e-06,
        "max_abs_error": 0.0006617835156532692,
        "rmse": 1.942749158063668e-05
      },
      {
        "seed": 45,
        "mean_abs_error": 3.2457090014784e-06,
        "max_abs_error": 0.0017435509641376967,
        "rmse": 5.736255701753222e-05
      },
      {
        "seed": 46,
        "mean_abs_error": 3.992184709109128e-05,
        "max_abs_error": 0.017945151819361627,
        "rmse": 0.0005180113171632565
      },
      {
        "seed": 47,
        "mean_abs_error": 4.391484051666689e-05,
        "max_abs_error": 0.025072111610825232,
        "rmse": 0.0007315273629694051
      },
      {
        "seed": 48,
        "mean_abs_error": 1.2140401927232574e-05,
        "max_abs_error": 0.0058192169058202126,
        "rmse": 0.00017713194943889246
      },
      {
        "seed": 49,
        "mean_abs_error": 9.313655470759752e-07,
        "max_abs_error": 0.0006177201077548489,
        "rmse": 1.770788081673687e-05
      },
      {
        "seed": 50,
        "mean_abs_error": 1.1864586152446928e-05,
        "max_abs_error": 0.00919841165139701,
        "rmse": 0.00023944383061675394
      },
      {
        "seed": 51,
        "mean_abs_error": 0.00016695874835413637,
        "max_abs_error": 0.05067282257241601,
        "rmse": 0.0017188928800733103
      },
      {
        "seed": 52,
        "mean_abs_error": 0.00010824960472470019,
        "max_abs_error": 0.039265980111089505,
        "rmse": 0.0013692052106331315
      },
      {
        "seed": 53,
        "mean_abs_error": 0.00010674180509360666,
        "max_abs_error": 0.016945546612575413,
        "rmse": 0.0009328518636825967
      },
      {
        "seed": 54,
        "mean_abs_error": 5.7273859022030976e-05,
        "max_abs_error": 0.0262753095175583,
        "rmse": 0.0008059615191469507
      },
      {
        "seed": 55,
        "mean_abs_error": 3.3711725538953566e-05,
        "max_abs_error": 0.022578299562667326,
        "rmse": 0.0006654310417389284
      },
      {
        "seed": 56,
        "mean_abs_error": 9.765324587952561e-05,
        "max_abs_error": 0.045323278702682046,
        "rmse": 0.0014320545170485154
      },
      {
        "seed": 57,
        "mean_abs_error": 7.869384589130076e-05,
        "max_abs_error": 0.02122435534099054,
        "rmse": 0.0009008861792845717
      },
      {
        "seed": 58,
        "mean_abs_error": 6.535828252694168e-05,
        "max_abs_error": 0.025131883335831162,
        "rmse": 0.0009055879180394222
      },
      {
        "seed": 59,
        "mean_abs_error": 8.031989270436537e-05,
        "max_abs_error": 0.020505626954332,
        "rmse": 0.0008034454428956486
      },
      {
        "seed": 60,
        "mean_abs_error": 3.1556134603351164e-05,
        "max_abs_error": 0.02071101638705386,
        "rmse": 0.0006032635802752455
      },
      {
        "seed": 61,
        "mean_abs_error": 5.346595856547326e-05,
        "max_abs_error": 0.03109311147477456,
        "rmse": 0.0009177796106560649
      },
      {
        "seed": 62,
        "mean_abs_error": 0.00010756245659597156,
        "max_abs_error": 0.038659828979348276,
        "rmse": 0.0013670396851663941
      },
      {
        "seed": 63,
        "mean_abs_error": 1.3288007436724316e-05,
        "max_abs_error": 0.00970624995098035,
        "rmse": 0.00025314109216468064
      },
      {
        "seed": 64,
        "mean_abs_error": 1.777900195287304e-05,
        "max_abs_error": 0.009975650669204583,
        "rmse": 0.00032061879759721164
      },
      {
        "seed": 65,
        "mean_abs_error": 9.34241627685938e-05,
        "max_abs_error": 0.02768760012401117,
        "rmse": 0.0010705907175986012
      },
      {
        "seed": 66,
        "mean_abs_error": 1.6817199893372401e-07,
        "max_abs_error": 0.00011016815007280911,
        "rmse": 3.4231096600787078e-06
      },
      {
        "seed": 67,
        "mean_abs_error": 1.4928974300971251e-05,
        "max_abs_error": 0.009893038419278355,
        "rmse": 0.00028509395811525585
      },
      {
        "seed": 68,
        "mean_abs_error": 0.0,
        "max_abs_error": 0.0,
        "rmse": 0.0
      },
      {
        "seed": 69,
        "mean_abs_error": 3.5510195727571504e-05,
        "max_abs_error": 0.02054056210411659,
        "rmse": 0.0006451827325501671
      },
      {
        "seed": 70,
        "mean_abs_error": 2.082807258475544e-05,
        "max_abs_error": 0.012392558555873734,
        "rmse": 0.0003955774221801344
      },
      {
        "seed": 71,
        "mean_abs_error": 9.028280725970541e-05,
        "max_abs_error": 0.05644679012299747,
        "rmse": 0.001720862368432083
      },
      {
        "seed": 72,
        "mean_abs_error": 5.329489132494662e-05,
        "max_abs_error": 0.020741938773937818,
        "rmse": 0.0006671386893589916
      },
      {
        "seed": 73,
        "mean_abs_error": 2.4680718429130223e-05,
        "max_abs_error": 0.01520452765927871,
        "rmse": 0.0004395658036153115
      },
      {
        "seed": 74,
        "mean_abs_error": 1.404513238485971e-08,
        "max_abs_error": 1.0056722231865933e-05,
        "rmse": 2.728184488019297e-07
      },
      {
        "seed": 75,
        "mean_abs_error": 2.0381385610122338e-05,
        "max_abs_error": 0.01453171663267483,
        "rmse": 0.0003637210273568831
      },
      {
        "seed": 76,
        "mean_abs_error": 5.606663827929134e-05,
        "max_abs_error": 0.02072771587161526,
        "rmse": 0.0007834273982138376
      },
      {
        "seed": 77,
        "mean_abs_error": 4.3195337879658485e-05,
        "max_abs_error": 0.01116681507627959,
        "rmse": 0.00046942048741599224
      },
      {
        "seed": 78,
        "mean_abs_error": 2.8035306631880218e-05,
        "max_abs_error": 0.018877035932248987,
        "rmse": 0.0005141588236224396
      },
      {
        "seed": 79,
        "mean_abs_error": 5.3229820703448656e-05,
        "max_abs_error": 0.021957137741971167,
        "rmse": 0.000772787664213978
      },
      {
        "seed": 80,
        "mean_abs_error": 9.862209656736548e-05,
        "max_abs_error": 0.024228802504538294,
        "rmse": 0.0009167317262529426
      },
      {
        "seed": 81,
        "mean_abs_error": 1.519422041289787e-06,
        "max_abs_error": 0.0010205295344434262,
        "rmse": 3.0666426048388674e-05
      },
      {
        "seed": 82,
        "mean_abs_error": 4.301737891488257e-05,
        "max_abs_error": 0.019510928127985494,
        "rmse": 0.000611891416611061
      },
      {
        "seed": 83,
        "mean_abs_error": 7.99780949821894e-06,
        "max_abs_error": 0.005630438780741542,
        "rmse": 0.0001581457269858172
      },
      {
        "seed": 84,
        "mean_abs_error": 2.591238675821604e-05,
        "max_abs_error": 0.018145587700288957,
        "rmse": 0.0005067348332105921
      },
      {
        "seed": 85,
        "mean_abs_error": 4.09778721439902e-05,
        "max_abs_error": 0.01969421733640786,
        "rmse": 0.000627083868347446
      },
      {
        "seed": 86,
        "mean_abs_error": 4.723510734869629e-06,
        "max_abs_error": 0.0026754075762909224,
        "rmse": 7.194780978430504e-05
      },
      {
        "seed": 87,
        "mean_abs_error": 5.2926005363311975e-05,
        "max_abs_error": 0.020149191950338263,
        "rmse": 0.0007262898776826867
      },
      {
        "seed": 88,
        "mean_abs_error": 2.1019084884619593e-05,
        "max_abs_error": 0.015164616107156803,
        "rmse": 0.00040828803654215123
      },
      {
        "seed": 89,
        "mean_abs_error": 3.419983788205556e-05,
        "max_abs_error": 0.022548182518875137,
        "rmse": 0.0006373907994735913
      },
      {
        "seed": 90,
        "mean_abs_error": 7.09250601096536e-05,
        "max_abs_error": 0.03179953372335831,
        "rmse": 0.001036602194480915
      },
      {
        "seed": 91,
        "mean_abs_error": 5.695944802544937e-05,
        "max_abs_error": 0.034884969942588384,
        "rmse": 0.0010725218746150706
      },
      {
        "seed": 92,
        "mean_abs_error": 0.00010170575082097709,
        "max_abs_error": 0.03869156726997858,
        "rmse": 0.001303723590293689
      },
      {
        "seed": 93,
        "mean_abs_error": 2.5809710276809295e-05,
        "max_abs_error": 0.010214305601323304,
        "rmse": 0.00031251606538110796
      },
      {
        "seed": 94,
        "mean_abs_error": 3.1496602507387445e-05,
        "max_abs_error": 0.021028990173547868,
        "rmse": 0.0005383064010043516
      },
      {
        "seed": 95,
        "mean_abs_error": 2.3173315082424727e-05,
        "max_abs_error": 0.019593017578969807,
        "rmse": 0.0004662863551523957
      },
      {
        "seed": 96,
        "mean_abs_error": 4.000510738682728e-08,
        "max_abs_error": 2.5762533056195025e-05,
        "rmse": 7.373216153513546e-07
      },
      {
        "seed": 97,
        "mean_abs_error": 0.0,
        "max_abs_error": 0.0,
        "rmse": 0.0
      },
      {
        "seed": 98,
        "mean_abs_error": 5.30834754419405e-05,
        "max_abs_error": 0.028018494750398304,
        "rmse": 0.0008255191220778327
      },
      {
        "seed": 99,
        "mean_abs_error": 5.660228512069189e-05,
        "max_abs_error": 0.017708065885592816,
        "rmse": 0.0006684018855784029
      }
    ],
    "s_fmt": "signed Q22.12",
    "score_fmt": "signed Q19.12",
    "m_fmt": "signed Q19.12",
    "log2e_fmt": "signed Q2.12",
    "exp_fmt": "UQ1.12",
    "locall_fmt": "UQ5.12",
    "l_fmt": "UQ9.12",
    "localo_fmt": "signed Q13.12",
    "oacc_fmt": "signed Q17.12"
  }
]